LICENSE.txt
MANIFEST.in
README.rst
setup.py
spa_sync/__init__.py
spa_sync/cli.py
spa_sync.egg-info/PKG-INFO
spa_sync.egg-info/SOURCES.txt
spa_sync.egg-info/dependency_links.txt
spa_sync.egg-info/entry_points.txt
spa_sync.egg-info/requires.txt
spa_sync.egg-info/top_level.txt
spa_sync/providers/__init__.py
spa_sync/providers/highrise.py
spa_sync/providers/contacts/__init__.py
spa_sync/providers/contacts/addressbook.py
spa_sync/providers/outlook/__init__.py
spa_sync/providers/outlook/client.py