Metadata-Version: 1.1
Name: spa-sync
Version: 0.1.0
Summary: Linksys/Sipura SPA IP Phone Sync
Home-page: http://github.com/Bouke/spa-sync
Author: Bouke Haarsma
Author-email: bouke@webatoom.nl
License: MIT
Platform: UNKNOWN
Classifier: Development Status :: 4 - Beta
Classifier: Intended Audience :: Developers
Classifier: License :: OSI Approved :: MIT License
Classifier: Operating System :: OS Independent
Classifier: Programming Language :: Python
Classifier: Topic :: Communications :: Internet Phone
